<?xml version="1.0" encoding="UTF-8" standalone="no"?>
<!DOCTYPE log SYSTEM "logger.dtd">
<log>
<record>
  <date>2019-12-20T15:43:55</date>
  <millis>1576853035070</millis>
  <sequence>1</sequence>
  <logger>wikiMain.class</logger>
  <level>INFO</level>
  <class>fr.istic.pdl1819_grp5.wikiMain</class>
  <method>main</method>
  <thread>1</thread>
  <message>entering of the function which find tables by criteria</message>
</record>
<record>
  <date>2019-12-20T15:43:55</date>
  <millis>1576853035071</millis>
  <sequence>2</sequence>
  <logger>wikiMain.class</logger>
  <level>INFO</level>
  <class>fr.istic.pdl1819_grp5.wikiMain</class>
  <method>main</method>
  <thread>1</thread>
  <message>Loading..........</message>
</record>
<record>
  <date>2019-12-20T15:43:55</date>
  <millis>1576853035072</millis>
  <sequence>3</sequence>
  <logger>wikiMain.class</logger>
  <level>INFO</level>
  <class>fr.istic.pdl1819_grp5.wikiMain</class>
  <method>main</method>
  <thread>1</thread>
  <message>end of searching table by criteria</message>
</record>
<record>
  <date>2019-12-20T15:43:55</date>
  <millis>1576853035073</millis>
  <sequence>4</sequence>
  <logger>wikiMain.class</logger>
  <level>FINER</level>
  <class>fr.istic.pdl1819_grp5.wikiMain</class>
  <method>getListofUrls</method>
  <thread>1</thread>
  <message>ENTRY inputdata\wikiurls.txt</message>
</record>
<record>
  <date>2019-12-20T15:44:44</date>
  <millis>1576853084705</millis>
  <sequence>5</sequence>
  <logger>wikiMain.class</logger>
  <level>FINER</level>
  <class>fr.istic.pdl1819_grp5.wikiMain</class>
  <method>getListofUrls</method>
  <thread>1</thread>
  <message>RETURN [fr.istic.pdl1819_grp5.UrlMatrix@3b084709, fr.istic.pdl1819_grp5.UrlMatrix@3327bd23, fr.istic.pdl1819_grp5.UrlMatrix@76a4d6c, fr.istic.pdl1819_grp5.UrlMatrix@12c8a2c0, fr.istic.pdl1819_grp5.UrlMatrix@31ef45e3, fr.istic.pdl1819_grp5.UrlMatrix@490ab905, fr.istic.pdl1819_grp5.UrlMatrix@5faeada1, fr.istic.pdl1819_grp5.UrlMatrix@64485a47, fr.istic.pdl1819_grp5.UrlMatrix@65e2dbf3, fr.istic.pdl1819_grp5.UrlMatrix@50b494a6, fr.istic.pdl1819_grp5.UrlMatrix@1e965684, fr.istic.pdl1819_grp5.UrlMatrix@5b87ed94, fr.istic.pdl1819_grp5.UrlMatrix@3578436e, fr.istic.pdl1819_grp5.UrlMatrix@6cc7b4de, fr.istic.pdl1819_grp5.UrlMatrix@25af5db5, fr.istic.pdl1819_grp5.UrlMatrix@1d371b2d, fr.istic.pdl1819_grp5.UrlMatrix@46238e3f, fr.istic.pdl1819_grp5.UrlMatrix@224edc67, fr.istic.pdl1819_grp5.UrlMatrix@2d8f65a4, fr.istic.pdl1819_grp5.UrlMatrix@60438a68, fr.istic.pdl1819_grp5.UrlMatrix@520a3426, fr.istic.pdl1819_grp5.UrlMatrix@61ca2dfa, fr.istic.pdl1819_grp5.UrlMatrix@4667ae56, fr.istic.pdl1819_grp5.UrlMatrix@4516af24, fr.istic.pdl1819_grp5.UrlMatrix@1ad282e0, fr.istic.pdl1819_grp5.UrlMatrix@6a4f787b, fr.istic.pdl1819_grp5.UrlMatrix@2bbf4b8b, fr.istic.pdl1819_grp5.UrlMatrix@48503868, fr.istic.pdl1819_grp5.UrlMatrix@6b57696f, fr.istic.pdl1819_grp5.UrlMatrix@5c072e3f, fr.istic.pdl1819_grp5.UrlMatrix@148080bb, fr.istic.pdl1819_grp5.UrlMatrix@4524411f, fr.istic.pdl1819_grp5.UrlMatrix@7d907bac, fr.istic.pdl1819_grp5.UrlMatrix@464bee09, fr.istic.pdl1819_grp5.UrlMatrix@436e852b, fr.istic.pdl1819_grp5.UrlMatrix@76707e36, fr.istic.pdl1819_grp5.UrlMatrix@31dc339b, fr.istic.pdl1819_grp5.UrlMatrix@290dbf45, fr.istic.pdl1819_grp5.UrlMatrix@10dba097, fr.istic.pdl1819_grp5.UrlMatrix@3043fe0e, fr.istic.pdl1819_grp5.UrlMatrix@1d7acb34, fr.istic.pdl1819_grp5.UrlMatrix@ae45eb6, fr.istic.pdl1819_grp5.UrlMatrix@32464a14, fr.istic.pdl1819_grp5.UrlMatrix@1f554b06, fr.istic.pdl1819_grp5.UrlMatrix@10d59286, fr.istic.pdl1819_grp5.UrlMatrix@396e2f39, fr.istic.pdl1819_grp5.UrlMatrix@2038ae61, fr.istic.pdl1819_grp5.UrlMatrix@1500955a, fr.istic.pdl1819_grp5.UrlMatrix@67b467e9, fr.istic.pdl1819_grp5.UrlMatrix@6fb0d3ed, fr.istic.pdl1819_grp5.UrlMatrix@6b09bb57, fr.istic.pdl1819_grp5.UrlMatrix@59fa1d9b, fr.istic.pdl1819_grp5.UrlMatrix@31610302, fr.istic.pdl1819_grp5.UrlMatrix@6b9651f3, fr.istic.pdl1819_grp5.UrlMatrix@3fee9989, fr.istic.pdl1819_grp5.UrlMatrix@5a8806ef, fr.istic.pdl1819_grp5.UrlMatrix@7403c468, fr.istic.pdl1819_grp5.UrlMatrix@1e7c7811, fr.istic.pdl1819_grp5.UrlMatrix@3a883ce7, fr.istic.pdl1819_grp5.UrlMatrix@589838eb, fr.istic.pdl1819_grp5.UrlMatrix@ea1a8d5, fr.istic.pdl1819_grp5.UrlMatrix@26aa12dd, fr.istic.pdl1819_grp5.UrlMatrix@33c7e1bb, fr.istic.pdl1819_grp5.UrlMatrix@731a74c, fr.istic.pdl1819_grp5.UrlMatrix@4fcd19b3, fr.istic.pdl1819_grp5.UrlMatrix@bd8db5a, fr.istic.pdl1819_grp5.UrlMatrix@cb644e, fr.istic.pdl1819_grp5.UrlMatrix@6500df86, fr.istic.pdl1819_grp5.UrlMatrix@5a8e6209, fr.istic.pdl1819_grp5.UrlMatrix@59906517, fr.istic.pdl1819_grp5.UrlMatrix@27efef64, fr.istic.pdl1819_grp5.UrlMatrix@3e9b1010, fr.istic.pdl1819_grp5.UrlMatrix@5b275dab, fr.istic.pdl1819_grp5.UrlMatrix@3108bc, fr.istic.pdl1819_grp5.UrlMatrix@365c30cc, fr.istic.pdl1819_grp5.UrlMatrix@c46bcd4, fr.istic.pdl1819_grp5.UrlMatrix@6c9f5c0d, fr.istic.pdl1819_grp5.UrlMatrix@467aecef, fr.istic.pdl1819_grp5.UrlMatrix@51cdd8a, fr.istic.pdl1819_grp5.UrlMatrix@4a87761d, fr.istic.pdl1819_grp5.UrlMatrix@64f6106c, fr.istic.pdl1819_grp5.UrlMatrix@58a90037, fr.istic.pdl1819_grp5.UrlMatrix@289d1c02, fr.istic.pdl1819_grp5.UrlMatrix@204f30ec, fr.istic.pdl1819_grp5.UrlMatrix@6950e31, fr.istic.pdl1819_grp5.UrlMatrix@687080dc, fr.istic.pdl1819_grp5.UrlMatrix@458c1321, fr.istic.pdl1819_grp5.UrlMatrix@b3d7190, fr.istic.pdl1819_grp5.UrlMatrix@4501b7af, fr.istic.pdl1819_grp5.UrlMatrix@5702b3b1, fr.istic.pdl1819_grp5.UrlMatrix@67b92f0a, fr.istic.pdl1819_grp5.UrlMatrix@4eb7f003, fr.istic.pdl1819_grp5.UrlMatrix@3439f68d, fr.istic.pdl1819_grp5.UrlMatrix@29b5cd00, fr.istic.pdl1819_grp5.UrlMatrix@6737fd8f, fr.istic.pdl1819_grp5.UrlMatrix@40f08448, fr.istic.pdl1819_grp5.UrlMatrix@2f0a87b3, fr.istic.pdl1819_grp5.UrlMatrix@7ba18f1b, fr.istic.pdl1819_grp5.UrlMatrix@3ffcd140, fr.istic.pdl1819_grp5.UrlMatrix@3abbfa04, fr.istic.pdl1819_grp5.UrlMatrix@7d70d1b1, fr.istic.pdl1819_grp5.UrlMatrix@543788f3, fr.istic.pdl1819_grp5.UrlMatrix@71bbf57e, fr.istic.pdl1819_grp5.UrlMatrix@4d3167f4, fr.istic.pdl1819_grp5.UrlMatrix@646d64ab, fr.istic.pdl1819_grp5.UrlMatrix@71d15f18, fr.istic.pdl1819_grp5.UrlMatrix@6325a3ee, fr.istic.pdl1819_grp5.UrlMatrix@31206beb, fr.istic.pdl1819_grp5.UrlMatrix@7a36aefa, fr.istic.pdl1819_grp5.UrlMatrix@704d6e83, fr.istic.pdl1819_grp5.UrlMatrix@13deb50e, fr.istic.pdl1819_grp5.UrlMatrix@5bcab519, fr.istic.pdl1819_grp5.UrlMatrix@1e88b3c, fr.istic.pdl1819_grp5.UrlMatrix@527740a2, fr.istic.pdl1819_grp5.UrlMatrix@5bcea91b, fr.istic.pdl1819_grp5.UrlMatrix@491cc5c9, fr.istic.pdl1819_grp5.UrlMatrix@7c29daf3, fr.istic.pdl1819_grp5.UrlMatrix@6f195bc3, fr.istic.pdl1819_grp5.UrlMatrix@4fe3c938, fr.istic.pdl1819_grp5.UrlMatrix@11c20519, fr.istic.pdl1819_grp5.UrlMatrix@4e41089d, fr.istic.pdl1819_grp5.UrlMatrix@69b0fd6f, fr.istic.pdl1819_grp5.UrlMatrix@5e853265, fr.istic.pdl1819_grp5.UrlMatrix@6a41eaa2, fr.istic.pdl1819_grp5.UrlMatrix@3712b94, fr.istic.pdl1819_grp5.UrlMatrix@70a9f84e, fr.istic.pdl1819_grp5.UrlMatrix@ff5b51f, fr.istic.pdl1819_grp5.UrlMatrix@68ceda24, fr.istic.pdl1819_grp5.UrlMatrix@544a2ea6, fr.istic.pdl1819_grp5.UrlMatrix@fcd6521, fr.istic.pdl1819_grp5.UrlMatrix@4b9e255, fr.istic.pdl1819_grp5.UrlMatrix@11e21d0e, fr.istic.pdl1819_grp5.UrlMatrix@612679d6, fr.istic.pdl1819_grp5.UrlMatrix@7d0587f1, fr.istic.pdl1819_grp5.UrlMatrix@799d4f69, fr.istic.pdl1819_grp5.UrlMatrix@371a67ec, fr.istic.pdl1819_grp5.UrlMatrix@5e5792a0, fr.istic.pdl1819_grp5.UrlMatrix@396f6598, fr.istic.pdl1819_grp5.UrlMatrix@6121c9d6, fr.istic.pdl1819_grp5.UrlMatrix@74a10858, fr.istic.pdl1819_grp5.UrlMatrix@27c20538, fr.istic.pdl1819_grp5.UrlMatrix@134593bf, fr.istic.pdl1819_grp5.UrlMatrix@5579bb86, fr.istic.pdl1819_grp5.UrlMatrix@64bf3bbf, fr.istic.pdl1819_grp5.UrlMatrix@4e9ba398, fr.istic.pdl1819_grp5.UrlMatrix@e720b71, fr.istic.pdl1819_grp5.UrlMatrix@27f723, fr.istic.pdl1819_grp5.UrlMatrix@2fd66ad3, fr.istic.pdl1819_grp5.UrlMatrix@23faf8f2, fr.istic.pdl1819_grp5.UrlMatrix@80503, fr.istic.pdl1819_grp5.UrlMatrix@5e25a92e, fr.istic.pdl1819_grp5.UrlMatrix@4f063c0a, fr.istic.pdl1819_grp5.UrlMatrix@29774679, fr.istic.pdl1819_grp5.UrlMatrix@2ac273d3, fr.istic.pdl1819_grp5.UrlMatrix@480bdb19, fr.istic.pdl1819_grp5.UrlMatrix@20322d26, fr.istic.pdl1819_grp5.UrlMatrix@7e2d773b, fr.istic.pdl1819_grp5.UrlMatrix@6e06451e, fr.istic.pdl1819_grp5.UrlMatrix@6ebc05a6, fr.istic.pdl1819_grp5.UrlMatrix@71623278, fr.istic.pdl1819_grp5.UrlMatrix@76b0bfab, fr.istic.pdl1819_grp5.UrlMatrix@954b04f, fr.istic.pdl1819_grp5.UrlMatrix@61f8bee4, fr.istic.pdl1819_grp5.UrlMatrix@4cf777e8, fr.istic.pdl1819_grp5.UrlMatrix@13eb8acf, fr.istic.pdl1819_grp5.UrlMatrix@7e9a5fbe, fr.istic.pdl1819_grp5.UrlMatrix@27a5f880, fr.istic.pdl1819_grp5.UrlMatrix@35d176f7, fr.istic.pdl1819_grp5.UrlMatrix@578486a3, fr.istic.pdl1819_grp5.UrlMatrix@44c8afef, fr.istic.pdl1819_grp5.UrlMatrix@2758fe70, fr.istic.pdl1819_grp5.UrlMatrix@1068e947, fr.istic.pdl1819_grp5.UrlMatrix@5123a213, fr.istic.pdl1819_grp5.UrlMatrix@6321e813, fr.istic.pdl1819_grp5.UrlMatrix@7e0b0338, fr.istic.pdl1819_grp5.UrlMatrix@5c5a1b69, fr.istic.pdl1819_grp5.UrlMatrix@679b62af, fr.istic.pdl1819_grp5.UrlMatrix@754ba872, fr.istic.pdl1819_grp5.UrlMatrix@7a9273a8, fr.istic.pdl1819_grp5.UrlMatrix@631330c, fr.istic.pdl1819_grp5.UrlMatrix@71a794e5, fr.istic.pdl1819_grp5.UrlMatrix@fad74ee, fr.istic.pdl1819_grp5.UrlMatrix@5f341870, fr.istic.pdl1819_grp5.UrlMatrix@1786dec2, fr.istic.pdl1819_grp5.UrlMatrix@587d1d39, fr.istic.pdl1819_grp5.UrlMatrix@3c0ecd4b, fr.istic.pdl1819_grp5.UrlMatrix@20398b7c, fr.istic.pdl1819_grp5.UrlMatrix@6adede5, fr.istic.pdl1819_grp5.UrlMatrix@6d4b1c02, fr.istic.pdl1819_grp5.UrlMatrix@23e028a9, fr.istic.pdl1819_grp5.UrlMatrix@4671e53b, fr.istic.pdl1819_grp5.UrlMatrix@3aeaafa6, fr.istic.pdl1819_grp5.UrlMatrix@66a3ffec, fr.istic.pdl1819_grp5.UrlMatrix@c81cdd1, fr.istic.pdl1819_grp5.UrlMatrix@1cab0bfb, fr.istic.pdl1819_grp5.UrlMatrix@103f852, fr.istic.pdl1819_grp5.UrlMatrix@5f9d02cb, fr.istic.pdl1819_grp5.UrlMatrix@3cb1ffe6, fr.istic.pdl1819_grp5.UrlMatrix@10bdf5e5, fr.istic.pdl1819_grp5.UrlMatrix@17579e0f, fr.istic.pdl1819_grp5.UrlMatrix@5abca1e0, fr.istic.pdl1819_grp5.UrlMatrix@6a1aab78, fr.istic.pdl1819_grp5.UrlMatrix@49fc609f, fr.istic.pdl1819_grp5.UrlMatrix@4dfa3a9d, fr.istic.pdl1819_grp5.UrlMatrix@101df177, fr.istic.pdl1819_grp5.UrlMatrix@5c3bd550, fr.istic.pdl1819_grp5.UrlMatrix@7085bdee, fr.istic.pdl1819_grp5.UrlMatrix@6043cd28, fr.istic.pdl1819_grp5.UrlMatrix@28ac3dc3, fr.istic.pdl1819_grp5.UrlMatrix@3d8314f0, fr.istic.pdl1819_grp5.UrlMatrix@2d127a61, fr.istic.pdl1819_grp5.UrlMatrix@4f7d0008, fr.istic.pdl1819_grp5.UrlMatrix@2641e737, fr.istic.pdl1819_grp5.UrlMatrix@4e7dc304, fr.istic.pdl1819_grp5.UrlMatrix@1d8d30f7, fr.istic.pdl1819_grp5.UrlMatrix@52feb982, fr.istic.pdl1819_grp5.UrlMatrix@b59d31, fr.istic.pdl1819_grp5.UrlMatrix@3f49dace, fr.istic.pdl1819_grp5.UrlMatrix@69a3d1d, fr.istic.pdl1819_grp5.UrlMatrix@50d0686, fr.istic.pdl1819_grp5.UrlMatrix@306279ee, fr.istic.pdl1819_grp5.UrlMatrix@5a4041cc, fr.istic.pdl1819_grp5.UrlMatrix@627551fb, fr.istic.pdl1819_grp5.UrlMatrix@17d0685f, fr.istic.pdl1819_grp5.UrlMatrix@1e127982, fr.istic.pdl1819_grp5.UrlMatrix@13c27452, fr.istic.pdl1819_grp5.UrlMatrix@cb0ed20, fr.istic.pdl1819_grp5.UrlMatrix@1da51a35, fr.istic.pdl1819_grp5.UrlMatrix@5bc79255, fr.istic.pdl1819_grp5.UrlMatrix@5f282abb, fr.istic.pdl1819_grp5.UrlMatrix@5f2108b5, fr.istic.pdl1819_grp5.UrlMatrix@33f88ab, fr.istic.pdl1819_grp5.UrlMatrix@588df31b, fr.istic.pdl1819_grp5.UrlMatrix@47c62251, fr.istic.pdl1819_grp5.UrlMatrix@5c18298f, fr.istic.pdl1819_grp5.UrlMatrix@56ef9176, fr.istic.pdl1819_grp5.UrlMatrix@46daef40, fr.istic.pdl1819_grp5.UrlMatrix@1176dcec, fr.istic.pdl1819_grp5.UrlMatrix@73846619, fr.istic.pdl1819_grp5.UrlMatrix@b9afc07, fr.istic.pdl1819_grp5.UrlMatrix@22a67b4, fr.istic.pdl1819_grp5.UrlMatrix@1e4a7dd4, fr.istic.pdl1819_grp5.UrlMatrix@eb21112, fr.istic.pdl1819_grp5.UrlMatrix@1c3a4799, fr.istic.pdl1819_grp5.UrlMatrix@710726a3, fr.istic.pdl1819_grp5.UrlMatrix@37d31475, fr.istic.pdl1819_grp5.UrlMatrix@1188e820, fr.istic.pdl1819_grp5.UrlMatrix@5025a98f, fr.istic.pdl1819_grp5.UrlMatrix@3bfdc050, fr.istic.pdl1819_grp5.UrlMatrix@56235b8e, fr.istic.pdl1819_grp5.UrlMatrix@184f6be2, fr.istic.pdl1819_grp5.UrlMatrix@78ac1102, fr.istic.pdl1819_grp5.UrlMatrix@2698dc7, fr.istic.pdl1819_grp5.UrlMatrix@53f65459, fr.istic.pdl1819_grp5.UrlMatrix@5700d6b1, fr.istic.pdl1819_grp5.UrlMatrix@548ad73b, fr.istic.pdl1819_grp5.UrlMatrix@46d56d67, fr.istic.pdl1819_grp5.UrlMatrix@3d921e20, fr.istic.pdl1819_grp5.UrlMatrix@aecb35a, fr.istic.pdl1819_grp5.UrlMatrix@4b952a2d, fr.istic.pdl1819_grp5.UrlMatrix@4abdb505, fr.istic.pdl1819_grp5.UrlMatrix@7494e528, fr.istic.pdl1819_grp5.UrlMatrix@530612ba, fr.istic.pdl1819_grp5.UrlMatrix@282003e1, fr.istic.pdl1819_grp5.UrlMatrix@133e16fd, fr.istic.pdl1819_grp5.UrlMatrix@612fc6eb, fr.istic.pdl1819_grp5.UrlMatrix@1a3869f4, fr.istic.pdl1819_grp5.UrlMatrix@3b94d659, fr.istic.pdl1819_grp5.UrlMatrix@45820e51, fr.istic.pdl1819_grp5.UrlMatrix@29ca901e, fr.istic.pdl1819_grp5.UrlMatrix@6ec8211c, fr.istic.pdl1819_grp5.UrlMatrix@17baae6e, fr.istic.pdl1819_grp5.UrlMatrix@1f7030a6, fr.istic.pdl1819_grp5.UrlMatrix@7a30d1e6, fr.istic.pdl1819_grp5.UrlMatrix@4fb64261, fr.istic.pdl1819_grp5.UrlMatrix@77a57272, fr.istic.pdl1819_grp5.UrlMatrix@24a35978, fr.istic.pdl1819_grp5.UrlMatrix@4cf4d528, fr.istic.pdl1819_grp5.UrlMatrix@8646db9, fr.istic.pdl1819_grp5.UrlMatrix@548e7350, fr.istic.pdl1819_grp5.UrlMatrix@63e2203c, fr.istic.pdl1819_grp5.UrlMatrix@78c03f1f, fr.istic.pdl1819_grp5.UrlMatrix@17776a8, fr.istic.pdl1819_grp5.UrlMatrix@34cd072c, fr.istic.pdl1819_grp5.UrlMatrix@32709393, fr.istic.pdl1819_grp5.UrlMatrix@6e1567f1, fr.istic.pdl1819_grp5.UrlMatrix@481a15ff, fr.istic.pdl1819_grp5.UrlMatrix@76b10754, fr.istic.pdl1819_grp5.UrlMatrix@536aaa8d, fr.istic.pdl1819_grp5.UrlMatrix@35a50a4c, fr.istic.pdl1819_grp5.UrlMatrix@9a7504c, fr.istic.pdl1819_grp5.UrlMatrix@53b32d7, fr.istic.pdl1819_grp5.UrlMatrix@365185bd, fr.istic.pdl1819_grp5.UrlMatrix@704921a5, fr.istic.pdl1819_grp5.UrlMatrix@d6da883, fr.istic.pdl1819_grp5.UrlMatrix@307f6b8c, fr.istic.pdl1819_grp5.UrlMatrix@782663d3, fr.istic.pdl1819_grp5.UrlMatrix@1877ab81, fr.istic.pdl1819_grp5.UrlMatrix@1a8a8f7c, fr.istic.pdl1819_grp5.UrlMatrix@610694f1, fr.istic.pdl1819_grp5.UrlMatrix@1442d7b5, fr.istic.pdl1819_grp5.UrlMatrix@27fe3806, fr.istic.pdl1819_grp5.UrlMatrix@50de0926, fr.istic.pdl1819_grp5.UrlMatrix@75881071, fr.istic.pdl1819_grp5.UrlMatrix@f4168b8, fr.istic.pdl1819_grp5.UrlMatrix@77f99a05, fr.istic.pdl1819_grp5.UrlMatrix@8b87145, fr.istic.pdl1819_grp5.UrlMatrix@52a86356, fr.istic.pdl1819_grp5.UrlMatrix@887af79, fr.istic.pdl1819_grp5.UrlMatrix@68bbe345, fr.istic.pdl1819_grp5.UrlMatrix@6eceb130]</message>
</record>
<record>
  <date>2019-12-20T15:44:44</date>
  <millis>1576853084719</millis>
  <sequence>6</sequence>
  <logger>wikiMain.class</logger>
  <level>INFO</level>
  <class>fr.istic.pdl1819_grp5.wikiMain</class>
  <method>main</method>
  <thread>1</thread>
  <message>Extracting via html...</message>
</record>
<record>
  <date>2019-12-20T15:45:28</date>
  <millis>1576853128726</millis>
  <sequence>7</sequence>
  <logger>wikiMain.class</logger>
  <level>FINER</level>
  <class>fr.istic.pdl1819_grp5.wikiMain</class>
  <method>getListofUrls</method>
  <thread>1</thread>
  <message>ENTRY inputdata\wikiurls.txt</message>
</record>
<record>
  <date>2019-12-20T15:46:19</date>
  <millis>1576853179273</millis>
  <sequence>8</sequence>
  <logger>wikiMain.class</logger>
  <level>FINER</level>
  <class>fr.istic.pdl1819_grp5.wikiMain</class>
  <method>getListofUrls</method>
  <thread>1</thread>
  <message>RETURN [fr.istic.pdl1819_grp5.UrlMatrix@4a07d605, fr.istic.pdl1819_grp5.UrlMatrix@70e38ce1, fr.istic.pdl1819_grp5.UrlMatrix@732d0d24, fr.istic.pdl1819_grp5.UrlMatrix@41ab013, fr.istic.pdl1819_grp5.UrlMatrix@7fcf2fc1, fr.istic.pdl1819_grp5.UrlMatrix@3b79fd76, fr.istic.pdl1819_grp5.UrlMatrix@7d9f158f, fr.istic.pdl1819_grp5.UrlMatrix@415b0b49, fr.istic.pdl1819_grp5.UrlMatrix@3fce8fd9, fr.istic.pdl1819_grp5.UrlMatrix@7daa0fbd, fr.istic.pdl1819_grp5.UrlMatrix@5b67bb7e, fr.istic.pdl1819_grp5.UrlMatrix@4167d97b, fr.istic.pdl1819_grp5.UrlMatrix@3eb77ea8, fr.istic.pdl1819_grp5.UrlMatrix@51c693d, fr.istic.pdl1819_grp5.UrlMatrix@64ec96c6, fr.istic.pdl1819_grp5.UrlMatrix@7bf3a5d8, fr.istic.pdl1819_grp5.UrlMatrix@4eaf3684, fr.istic.pdl1819_grp5.UrlMatrix@16612a51, fr.istic.pdl1819_grp5.UrlMatrix@6c7a164b, fr.istic.pdl1819_grp5.UrlMatrix@2c78324b, fr.istic.pdl1819_grp5.UrlMatrix@4278284b, fr.istic.pdl1819_grp5.UrlMatrix@258d79be, fr.istic.pdl1819_grp5.UrlMatrix@7d61eb55, fr.istic.pdl1819_grp5.UrlMatrix@14f232c4, fr.istic.pdl1819_grp5.UrlMatrix@45ac5f9b, fr.istic.pdl1819_grp5.UrlMatrix@1722011b, fr.istic.pdl1819_grp5.UrlMatrix@6bc407fd, fr.istic.pdl1819_grp5.UrlMatrix@17503f6b, fr.istic.pdl1819_grp5.UrlMatrix@5852c06f, fr.istic.pdl1819_grp5.UrlMatrix@1df8b5b8, fr.istic.pdl1819_grp5.UrlMatrix@1a5a4e19, fr.istic.pdl1819_grp5.UrlMatrix@3116c353, fr.istic.pdl1819_grp5.UrlMatrix@58594a11, fr.istic.pdl1819_grp5.UrlMatrix@2bdd8394, fr.istic.pdl1819_grp5.UrlMatrix@53f3bdbd, fr.istic.pdl1819_grp5.UrlMatrix@490caf5f, fr.istic.pdl1819_grp5.UrlMatrix@6692b6c6, fr.istic.pdl1819_grp5.UrlMatrix@127a7a2e, fr.istic.pdl1819_grp5.UrlMatrix@1ae8bcbc, fr.istic.pdl1819_grp5.UrlMatrix@52e7a6b2, fr.istic.pdl1819_grp5.UrlMatrix@1b8a29df, fr.istic.pdl1819_grp5.UrlMatrix@27d5a580, fr.istic.pdl1819_grp5.UrlMatrix@463fd068, fr.istic.pdl1819_grp5.UrlMatrix@79c97cb, fr.istic.pdl1819_grp5.UrlMatrix@59e505b2, fr.istic.pdl1819_grp5.UrlMatrix@2205a05d, fr.istic.pdl1819_grp5.UrlMatrix@4ef782af, fr.istic.pdl1819_grp5.UrlMatrix@7674b62c, fr.istic.pdl1819_grp5.UrlMatrix@38ba6ce3, fr.istic.pdl1819_grp5.UrlMatrix@3f67593e, fr.istic.pdl1819_grp5.UrlMatrix@488d1cd7, fr.istic.pdl1819_grp5.UrlMatrix@4c5ae43b, fr.istic.pdl1819_grp5.UrlMatrix@638ef7ed, fr.istic.pdl1819_grp5.UrlMatrix@4d518b32, fr.istic.pdl1819_grp5.UrlMatrix@7b50df34, fr.istic.pdl1819_grp5.UrlMatrix@2e48362c, fr.istic.pdl1819_grp5.UrlMatrix@730d2164, fr.istic.pdl1819_grp5.UrlMatrix@7de62196, fr.istic.pdl1819_grp5.UrlMatrix@3fa247d1, fr.istic.pdl1819_grp5.UrlMatrix@68702e03, fr.istic.pdl1819_grp5.UrlMatrix@3370f42, fr.istic.pdl1819_grp5.UrlMatrix@4b8729ff, fr.istic.pdl1819_grp5.UrlMatrix@f99f5e0, fr.istic.pdl1819_grp5.UrlMatrix@5be46f9d, fr.istic.pdl1819_grp5.UrlMatrix@6cb6decd, fr.istic.pdl1819_grp5.UrlMatrix@e3c0e40, fr.istic.pdl1819_grp5.UrlMatrix@301eda63, fr.istic.pdl1819_grp5.UrlMatrix@2609b277, fr.istic.pdl1819_grp5.UrlMatrix@662706a7, fr.istic.pdl1819_grp5.UrlMatrix@6f3187b0, fr.istic.pdl1819_grp5.UrlMatrix@59e32960, fr.istic.pdl1819_grp5.UrlMatrix@5be49b60, fr.istic.pdl1819_grp5.UrlMatrix@2421cc4, fr.istic.pdl1819_grp5.UrlMatrix@2ad48653, fr.istic.pdl1819_grp5.UrlMatrix@38af9828, fr.istic.pdl1819_grp5.UrlMatrix@205d38da, fr.istic.pdl1819_grp5.UrlMatrix@b978d10, fr.istic.pdl1819_grp5.UrlMatrix@50dfbc58, fr.istic.pdl1819_grp5.UrlMatrix@1984b1f, fr.istic.pdl1819_grp5.UrlMatrix@332729ad, fr.istic.pdl1819_grp5.UrlMatrix@266374ef, fr.istic.pdl1819_grp5.UrlMatrix@5a5338df, fr.istic.pdl1819_grp5.UrlMatrix@5038d0b5, fr.istic.pdl1819_grp5.UrlMatrix@6c0d7c83, fr.istic.pdl1819_grp5.UrlMatrix@1f53a5dc, fr.istic.pdl1819_grp5.UrlMatrix@2d6c53fc, fr.istic.pdl1819_grp5.UrlMatrix@1339e7aa, fr.istic.pdl1819_grp5.UrlMatrix@cd1e646, fr.istic.pdl1819_grp5.UrlMatrix@28b46423, fr.istic.pdl1819_grp5.UrlMatrix@147e2ae7, fr.istic.pdl1819_grp5.UrlMatrix@27912e3, fr.istic.pdl1819_grp5.UrlMatrix@6c4980d3, fr.istic.pdl1819_grp5.UrlMatrix@54504ecd, fr.istic.pdl1819_grp5.UrlMatrix@73302995, fr.istic.pdl1819_grp5.UrlMatrix@71329995, fr.istic.pdl1819_grp5.UrlMatrix@12a94400, fr.istic.pdl1819_grp5.UrlMatrix@455b6df1, fr.istic.pdl1819_grp5.UrlMatrix@6f1c29b7, fr.istic.pdl1819_grp5.UrlMatrix@1d483de4, fr.istic.pdl1819_grp5.UrlMatrix@7975d1d8, fr.istic.pdl1819_grp5.UrlMatrix@10289886, fr.istic.pdl1819_grp5.UrlMatrix@4ebff610, fr.istic.pdl1819_grp5.UrlMatrix@3403e2ac, fr.istic.pdl1819_grp5.UrlMatrix@6b58b9e9, fr.istic.pdl1819_grp5.UrlMatrix@be68757, fr.istic.pdl1819_grp5.UrlMatrix@24c22fe, fr.istic.pdl1819_grp5.UrlMatrix@21d03963, fr.istic.pdl1819_grp5.UrlMatrix@727eb8cb, fr.istic.pdl1819_grp5.UrlMatrix@125290e5, fr.istic.pdl1819_grp5.UrlMatrix@12359a82, fr.istic.pdl1819_grp5.UrlMatrix@225129c, fr.istic.pdl1819_grp5.UrlMatrix@a307a8c, fr.istic.pdl1819_grp5.UrlMatrix@57576994, fr.istic.pdl1819_grp5.UrlMatrix@27adc16e, fr.istic.pdl1819_grp5.UrlMatrix@1bae316d, fr.istic.pdl1819_grp5.UrlMatrix@4ef74c30, fr.istic.pdl1819_grp5.UrlMatrix@723e88f9, fr.istic.pdl1819_grp5.UrlMatrix@a37aefe, fr.istic.pdl1819_grp5.UrlMatrix@3ddc6915, fr.istic.pdl1819_grp5.UrlMatrix@42b3b079, fr.istic.pdl1819_grp5.UrlMatrix@6986852, fr.istic.pdl1819_grp5.UrlMatrix@341814d3, fr.istic.pdl1819_grp5.UrlMatrix@4b34fff9, fr.istic.pdl1819_grp5.UrlMatrix@7dc3712, fr.istic.pdl1819_grp5.UrlMatrix@436c81a3, fr.istic.pdl1819_grp5.UrlMatrix@12d2ce03, fr.istic.pdl1819_grp5.UrlMatrix@62833051, fr.istic.pdl1819_grp5.UrlMatrix@39b43d60, fr.istic.pdl1819_grp5.UrlMatrix@481ba2cf, fr.istic.pdl1819_grp5.UrlMatrix@60db1c0e, fr.istic.pdl1819_grp5.UrlMatrix@6676f6a0, fr.istic.pdl1819_grp5.UrlMatrix@31add175, fr.istic.pdl1819_grp5.UrlMatrix@478db956, fr.istic.pdl1819_grp5.UrlMatrix@55cf0d14, fr.istic.pdl1819_grp5.UrlMatrix@6f7923a5, fr.istic.pdl1819_grp5.UrlMatrix@3cfdd820, fr.istic.pdl1819_grp5.UrlMatrix@4ff8d125, fr.istic.pdl1819_grp5.UrlMatrix@4e423aa2, fr.istic.pdl1819_grp5.UrlMatrix@3e44f2a5, fr.istic.pdl1819_grp5.UrlMatrix@6c2ed0cd, fr.istic.pdl1819_grp5.UrlMatrix@26df6e3a, fr.istic.pdl1819_grp5.UrlMatrix@1cf56a1c, fr.istic.pdl1819_grp5.UrlMatrix@20f5281c, fr.istic.pdl1819_grp5.UrlMatrix@a1f72f5, fr.istic.pdl1819_grp5.UrlMatrix@68f4865, fr.istic.pdl1819_grp5.UrlMatrix@17d88132, fr.istic.pdl1819_grp5.UrlMatrix@18317edc, fr.istic.pdl1819_grp5.UrlMatrix@59d4cd39, fr.istic.pdl1819_grp5.UrlMatrix@3fc79729, fr.istic.pdl1819_grp5.UrlMatrix@3697186, fr.istic.pdl1819_grp5.UrlMatrix@1672fe87, fr.istic.pdl1819_grp5.UrlMatrix@4196c360, fr.istic.pdl1819_grp5.UrlMatrix@51a9ad5e, fr.istic.pdl1819_grp5.UrlMatrix@2b72cb8a, fr.istic.pdl1819_grp5.UrlMatrix@13d4992d, fr.istic.pdl1819_grp5.UrlMatrix@45a37759, fr.istic.pdl1819_grp5.UrlMatrix@21ba0741, fr.istic.pdl1819_grp5.UrlMatrix@4b5189ac, fr.istic.pdl1819_grp5.UrlMatrix@16aa8654, fr.istic.pdl1819_grp5.UrlMatrix@6f19ac19, fr.istic.pdl1819_grp5.UrlMatrix@1115ec15, fr.istic.pdl1819_grp5.UrlMatrix@6e15fe2, fr.istic.pdl1819_grp5.UrlMatrix@5e403b4a, fr.istic.pdl1819_grp5.UrlMatrix@5454d35e, fr.istic.pdl1819_grp5.UrlMatrix@13526e59, fr.istic.pdl1819_grp5.UrlMatrix@27508c5d, fr.istic.pdl1819_grp5.UrlMatrix@7f2cfe3f, fr.istic.pdl1819_grp5.UrlMatrix@e3b3b2f, fr.istic.pdl1819_grp5.UrlMatrix@2812b107, fr.istic.pdl1819_grp5.UrlMatrix@2b175c00, fr.istic.pdl1819_grp5.UrlMatrix@18ece7f4, fr.istic.pdl1819_grp5.UrlMatrix@49c66ade, fr.istic.pdl1819_grp5.UrlMatrix@43599640, fr.istic.pdl1819_grp5.UrlMatrix@19c65cdc, fr.istic.pdl1819_grp5.UrlMatrix@59a008ba, fr.istic.pdl1819_grp5.UrlMatrix@6304101a, fr.istic.pdl1819_grp5.UrlMatrix@16c069df, fr.istic.pdl1819_grp5.UrlMatrix@3b6d844d, fr.istic.pdl1819_grp5.UrlMatrix@c667f46, fr.istic.pdl1819_grp5.UrlMatrix@35645047, fr.istic.pdl1819_grp5.UrlMatrix@28d18df5, fr.istic.pdl1819_grp5.UrlMatrix@7d3d101b, fr.istic.pdl1819_grp5.UrlMatrix@379614be, fr.istic.pdl1819_grp5.UrlMatrix@41005828, fr.istic.pdl1819_grp5.UrlMatrix@7164ca4c, fr.istic.pdl1819_grp5.UrlMatrix@10f7f7de, fr.istic.pdl1819_grp5.UrlMatrix@461ad730, fr.istic.pdl1819_grp5.UrlMatrix@3406472c, fr.istic.pdl1819_grp5.UrlMatrix@600b9d27, fr.istic.pdl1819_grp5.UrlMatrix@7d94beb9, fr.istic.pdl1819_grp5.UrlMatrix@4e928fbf, fr.istic.pdl1819_grp5.UrlMatrix@4671115f, fr.istic.pdl1819_grp5.UrlMatrix@5b367418, fr.istic.pdl1819_grp5.UrlMatrix@7f284218, fr.istic.pdl1819_grp5.UrlMatrix@5c45d770, fr.istic.pdl1819_grp5.UrlMatrix@44d52de2, fr.istic.pdl1819_grp5.UrlMatrix@471a9022, fr.istic.pdl1819_grp5.UrlMatrix@2796aeae, fr.istic.pdl1819_grp5.UrlMatrix@e25951c, fr.istic.pdl1819_grp5.UrlMatrix@6d07a63d, fr.istic.pdl1819_grp5.UrlMatrix@35a3d49f, fr.istic.pdl1819_grp5.UrlMatrix@1130520d, fr.istic.pdl1819_grp5.UrlMatrix@3f1d2e23, fr.istic.pdl1819_grp5.UrlMatrix@f107c50, fr.istic.pdl1819_grp5.UrlMatrix@2b9ed6da, fr.istic.pdl1819_grp5.UrlMatrix@5965be2d, fr.istic.pdl1819_grp5.UrlMatrix@457c9034, fr.istic.pdl1819_grp5.UrlMatrix@311bf055, fr.istic.pdl1819_grp5.UrlMatrix@72ade7e3, fr.istic.pdl1819_grp5.UrlMatrix@518caac3, fr.istic.pdl1819_grp5.UrlMatrix@2474f125, fr.istic.pdl1819_grp5.UrlMatrix@13df2a8c, fr.istic.pdl1819_grp5.UrlMatrix@3224a577, fr.istic.pdl1819_grp5.UrlMatrix@68746f22, fr.istic.pdl1819_grp5.UrlMatrix@30b6ffe0, fr.istic.pdl1819_grp5.UrlMatrix@5d43661b, fr.istic.pdl1819_grp5.UrlMatrix@78a773fd, fr.istic.pdl1819_grp5.UrlMatrix@4e31276e, fr.istic.pdl1819_grp5.UrlMatrix@172b013, fr.istic.pdl1819_grp5.UrlMatrix@4c012563, fr.istic.pdl1819_grp5.UrlMatrix@2462cb01, fr.istic.pdl1819_grp5.UrlMatrix@1b266842, fr.istic.pdl1819_grp5.UrlMatrix@bb9e6dc, fr.istic.pdl1819_grp5.UrlMatrix@1205bd62, fr.istic.pdl1819_grp5.UrlMatrix@43015c69, fr.istic.pdl1819_grp5.UrlMatrix@24c4ddae, fr.istic.pdl1819_grp5.UrlMatrix@72d6b3ba, fr.istic.pdl1819_grp5.UrlMatrix@589da3f3, fr.istic.pdl1819_grp5.UrlMatrix@769a1df5, fr.istic.pdl1819_grp5.UrlMatrix@563e4951, fr.istic.pdl1819_grp5.UrlMatrix@4b213651, fr.istic.pdl1819_grp5.UrlMatrix@238d68ff, fr.istic.pdl1819_grp5.UrlMatrix@456d6c1e, fr.istic.pdl1819_grp5.UrlMatrix@a82c5f1, fr.istic.pdl1819_grp5.UrlMatrix@47c81abf, fr.istic.pdl1819_grp5.UrlMatrix@69f1a286, fr.istic.pdl1819_grp5.UrlMatrix@35399441, fr.istic.pdl1819_grp5.UrlMatrix@479cbee5, fr.istic.pdl1819_grp5.UrlMatrix@4f74980d, fr.istic.pdl1819_grp5.UrlMatrix@64e7619d, fr.istic.pdl1819_grp5.UrlMatrix@6cc4cdb9, fr.istic.pdl1819_grp5.UrlMatrix@42a15bdc, fr.istic.pdl1819_grp5.UrlMatrix@3336e6b6, fr.istic.pdl1819_grp5.UrlMatrix@766653e6, fr.istic.pdl1819_grp5.UrlMatrix@62656be4, fr.istic.pdl1819_grp5.UrlMatrix@5e3f861, fr.istic.pdl1819_grp5.UrlMatrix@b86de0d, fr.istic.pdl1819_grp5.UrlMatrix@56dc1551, fr.istic.pdl1819_grp5.UrlMatrix@3e2059ae, fr.istic.pdl1819_grp5.UrlMatrix@31edaa7d, fr.istic.pdl1819_grp5.UrlMatrix@7354b8c5, fr.istic.pdl1819_grp5.UrlMatrix@658c5a19, fr.istic.pdl1819_grp5.UrlMatrix@48793bef, fr.istic.pdl1819_grp5.UrlMatrix@48d61b48, fr.istic.pdl1819_grp5.UrlMatrix@7d322cad, fr.istic.pdl1819_grp5.UrlMatrix@7098b907, fr.istic.pdl1819_grp5.UrlMatrix@3c01cfa1, fr.istic.pdl1819_grp5.UrlMatrix@1787bc24, fr.istic.pdl1819_grp5.UrlMatrix@4470fbd6, fr.istic.pdl1819_grp5.UrlMatrix@4ea5b703, fr.istic.pdl1819_grp5.UrlMatrix@39ac0c0a, fr.istic.pdl1819_grp5.UrlMatrix@6b6776cb, fr.istic.pdl1819_grp5.UrlMatrix@3081f72c, fr.istic.pdl1819_grp5.UrlMatrix@4fa1c212, fr.istic.pdl1819_grp5.UrlMatrix@50313382, fr.istic.pdl1819_grp5.UrlMatrix@7aaca91a, fr.istic.pdl1819_grp5.UrlMatrix@30bce90b, fr.istic.pdl1819_grp5.UrlMatrix@1b45c0e, fr.istic.pdl1819_grp5.UrlMatrix@7393222f, fr.istic.pdl1819_grp5.UrlMatrix@6aa8e115, fr.istic.pdl1819_grp5.UrlMatrix@16b2bb0c, fr.istic.pdl1819_grp5.UrlMatrix@d771cc9, fr.istic.pdl1819_grp5.UrlMatrix@16eccb2e, fr.istic.pdl1819_grp5.UrlMatrix@747f281, fr.istic.pdl1819_grp5.UrlMatrix@59cba5a, fr.istic.pdl1819_grp5.UrlMatrix@3214ee6, fr.istic.pdl1819_grp5.UrlMatrix@6e005dc9, fr.istic.pdl1819_grp5.UrlMatrix@420a85c4, fr.istic.pdl1819_grp5.UrlMatrix@5c669da8, fr.istic.pdl1819_grp5.UrlMatrix@3e74829, fr.istic.pdl1819_grp5.UrlMatrix@49b2a47d, fr.istic.pdl1819_grp5.UrlMatrix@4a00d9cf, fr.istic.pdl1819_grp5.UrlMatrix@48b67364, fr.istic.pdl1819_grp5.UrlMatrix@573906eb, fr.istic.pdl1819_grp5.UrlMatrix@64b0598, fr.istic.pdl1819_grp5.UrlMatrix@24105dc5, fr.istic.pdl1819_grp5.UrlMatrix@2ca26d77, fr.istic.pdl1819_grp5.UrlMatrix@20ca951f, fr.istic.pdl1819_grp5.UrlMatrix@5a3bc7ed, fr.istic.pdl1819_grp5.UrlMatrix@27e47833, fr.istic.pdl1819_grp5.UrlMatrix@78aa1f72, fr.istic.pdl1819_grp5.UrlMatrix@2f666ebb, fr.istic.pdl1819_grp5.UrlMatrix@5cdec700, fr.istic.pdl1819_grp5.UrlMatrix@6b0d80ed, fr.istic.pdl1819_grp5.UrlMatrix@1e81f160, fr.istic.pdl1819_grp5.UrlMatrix@8e50104, fr.istic.pdl1819_grp5.UrlMatrix@38604b81, fr.istic.pdl1819_grp5.UrlMatrix@797b0699, fr.istic.pdl1819_grp5.UrlMatrix@6bf08014, fr.istic.pdl1819_grp5.UrlMatrix@4f49f6af, fr.istic.pdl1819_grp5.UrlMatrix@7cb502c, fr.istic.pdl1819_grp5.UrlMatrix@35b74c5c, fr.istic.pdl1819_grp5.UrlMatrix@9cb8225, fr.istic.pdl1819_grp5.UrlMatrix@43b9fd5, fr.istic.pdl1819_grp5.UrlMatrix@1ec9bd38, fr.istic.pdl1819_grp5.UrlMatrix@3e2055d6, fr.istic.pdl1819_grp5.UrlMatrix@55c53a33, fr.istic.pdl1819_grp5.UrlMatrix@3b8f0a79, fr.istic.pdl1819_grp5.UrlMatrix@18e36d14, fr.istic.pdl1819_grp5.UrlMatrix@7b993c65, fr.istic.pdl1819_grp5.UrlMatrix@1890516e]</message>
</record>
<record>
  <date>2019-12-20T15:46:19</date>
  <millis>1576853179277</millis>
  <sequence>9</sequence>
  <logger>wikiMain.class</logger>
  <level>INFO</level>
  <class>fr.istic.pdl1819_grp5.wikiMain</class>
  <method>main</method>
  <thread>1</thread>
  <message>Extracting via wikitext...</message>
</record>
</log>
